4:1 Multiplexer/mux_41.v
module mux_41(
    input a, b, c, d,
    input s1, s0,
    output y
);

assign y = s1 ? (s0 ? d:c) : (s0 ? b:a);

endmodule

4:1 Multiplexer/mux_41_tb.v
`timescale 1ns/1ps

module mux_41_tb;

reg a, b, c, d;
reg s1, s0;

wire y;

mux_41 uut (
    .a(a),
    .b(b),
    .c(c),
    .d(d),
    .s1(s1),
    .s0(s0),
    .y(y)
);

initial begin
   //Create waveform file for GTK Wave
   $dumpfile("mux_41.vcd");
   $dumpvars(0, mux_41_tb);

//Input values
//Test case 1: a =0, b=1, c=0, d=1
    a=0;
    b=1;
    c=0;
    d=1;

    s1=0; s0=0; #10;
    s1=0; s0=1; #10;
    s1=1; s0=0; #10;
    s1=1; s0=1; #10;

    //Test Case 2: Reverse Input Waveform
    // a =1, b=0, c=1, d=0
    a=1; 
    b=0; 
    c=1;
    d=0;

    s1=0; s0=0; #10;
    s1=0; s0=1; #10;
    s1=1; s0=0; #10;
    s1=1; s0=1; #10;

    $finish;

end 

endmodule

4:1 Multiplexer/mux_41.vcd
$date
	Fri Oct 02 19:30:57 2026
$end
$version
	Icarus Verilog
$end
$timescale
	1ps
$end
$scope module mux_41_tb $end
$var wire 1 ! y $end
$var reg 1 " a $end
$var reg 1 # b $end
$var reg 1 $ c $end
$var reg 1 % d $end
$var reg 1 & s0 $end
$var reg 1 ' s1 $end
$scope module uut $end
$var wire 1 " a $end
$var wire 1 # b $end
$var wire 1 $ c $end
$var wire 1 % d $end
$var wire 1 & s0 $end
$var wire 1 ' s1 $end
$var wire 1 ! y $end
$upscope $end
$upscope $end
$enddefinitions $end
$comment Show the parameter values. $end
$dumpall
$end
#0
$dumpvars
0'
0&
1%
0$
1#
0"
0!
$end
#10000
1!
1&
#20000
0!
0&
1'
#30000
1!
1&
#40000
0&
0'
0%
1$
0#
1"
#50000
0!
1&
#60000
1!
0&
1'
#70000
0!
1&
